{
  "navItems": [
    {
      "navId": 1,
      "name": "Sponsor a Child",
      "childOf": 0
    },
    {
      "navId": 2,
      "name": "View Longest Waiting",
      "childOf": 1
    },
    {
      "navId": 3,
      "name": "View All Children",
      "childOf": 1
    },
    {
      "navId": 4,
      "name": "Why Sponsor?",
      "childOf": 1
    },
    {
      "navId": 5,
      "name": "testSub",
      "childOf": 4
    },
    {
      "navId": 6,
      "name": "Ways to Donate",
      "childOf": 0
    },
    {
      "navId": 7,
      "name": "Meet Critical Needs",
      "childOf": 6
    },
    {
      "navId": 8,
      "name": "Help Babies",
      "childOf": 6
    }
  ]
}
